tsalab/__init__.py
tsalab/main.py
tsalab/codes/1.txt
tsalab/codes/2.txt
tsalab/codes/3.txt
tsalab/codes/4.txt
tsalab/codes/5.txt
tsalab-0.0.7.dist-info/METADATA
tsalab-0.0.7.dist-info/WHEEL
tsalab-0.0.7.dist-info/top_level.txt
tsalab-0.0.7.dist-info/RECORD
