Metadata-Version: 2.4
Name: tsalab
Version: 0.0.7
Summary: A Python package that retrieves code snippets by number
Author: tsalab
License: MIT
